{
  "usableSessionsCount": 32,
  "retiredSessionsCount": 0,
  "sessions": [
    {
      "id": "session_ihUSdPKXsa",
      "cookieJar": {
        "version": "tough-cookie@5.1.2",
        "storeType": "MemoryCookieStore",
        "rejectPublicSuffixes": true,
        "enableLooseMode": false,
        "allowSpecialUseDomain": true,
        "prefixSecurity": "silent",
        "cookies": [
          {
            "key": "PHPSESSID",
            "value": "chi0mebuc8m059dluhe4ba4i0k",
            "domain": "b2b.daisan.vn",
            "path": "/",
            "hostOnly": true,
            "creation": "2025-08-08T07:09:53.703Z",
            "lastAccessed": "2025-08-08T07:09:53.703Z"
          }
        ]
      },
      "userData": {},
      "maxErrorScore": 3,
      "errorScoreDecrement": 0.5,
      "expiresAt": "2025-08-08T07:59:53.386Z",
      "createdAt": "2025-08-08T07:09:53.386Z",
      "usageCount": 1,
      "maxUsageCount": 50,
      "errorScore": 0
    },
    {
      "id": "session_h9dIdB8ngR",
      "cookieJar": {
        "version": "tough-cookie@5.1.2",
        "storeType": "MemoryCookieStore",
        "rejectPublicSuffixes": true,
        "enableLooseMode": false,
        "allowSpecialUseDomain": true,
        "prefixSecurity": "silent",
        "cookies": [
          {
            "key": "PHPSESSID",
            "value": "v3chk804vpsh9ucjfr4gjkl5ma",
            "domain": "b2b.daisan.vn",
            "path": "/",
            "hostOnly": true,
            "creation": "2025-08-08T07:09:53.990Z",
            "lastAccessed": "2025-08-08T07:09:53.990Z"
          }
        ]
      },
      "userData": {},
      "maxErrorScore": 3,
      "errorScoreDecrement": 0.5,
      "expiresAt": "2025-08-08T07:59:53.863Z",
      "createdAt": "2025-08-08T07:09:53.863Z",
      "usageCount": 1,
      "maxUsageCount": 50,
      "errorScore": 0
    },
    {
      "id": "session_eCo8utnSQk",
      "cookieJar": {
        "version": "tough-cookie@5.1.2",
        "storeType": "MemoryCookieStore",
        "rejectPublicSuffixes": true,
        "enableLooseMode": false,
        "allowSpecialUseDomain": true,
        "prefixSecurity": "silent",
        "cookies": [
          {
            "key": "PHPSESSID",
            "value": "3028fb8rq96tpiaa4bt982shi3",
            "domain": "b2b.daisan.vn",
            "path": "/",
            "hostOnly": true,
            "creation": "2025-08-08T07:09:54.165Z",
            "lastAccessed": "2025-08-08T07:09:54.165Z"
          },
          {
            "key": "HodineCache",
            "value": "%7B%22product_view%22%3A%5B%22479070%22%5D%2C%22category_view%22%3A%5B70%5D%7D",
            "expires": "2028-01-25T07:09:55.000Z",
            "maxAge": 77760000,
            "domain": "b2b.daisan.vn",
            "path": "/",
            "hostOnly": true,
            "creation": "2025-08-08T07:09:54.165Z",
            "lastAccessed": "2025-08-08T07:09:54.165Z"
          }
        ]
      },
      "userData": {},
      "maxErrorScore": 3,
      "errorScoreDecrement": 0.5,
      "expiresAt": "2025-08-08T07:59:53.867Z",
      "createdAt": "2025-08-08T07:09:53.867Z",
      "usageCount": 1,
      "maxUsageCount": 50,
      "errorScore": 0
    },
    {
      "id": "session_FHHCpoMoqA",
      "cookieJar": {
        "version": "tough-cookie@5.1.2",
        "storeType": "MemoryCookieStore",
        "rejectPublicSuffixes": true,
        "enableLooseMode": false,
        "allowSpecialUseDomain": true,
        "prefixSecurity": "silent",
        "cookies": [
          {
            "key": "PHPSESSID",
            "value": "5i9r9aue8ovn4uem35dqiold7l",
            "domain": "b2b.daisan.vn",
            "path": "/",
            "hostOnly": true,
            "creation": "2025-08-08T07:09:54.205Z",
            "lastAccessed": "2025-08-08T07:09:54.205Z"
          },
          {
            "key": "HodineCache",
            "value": "%7B%22product_view%22%3A%5B%22657943%22%5D%2C%22category_view%22%3A%5B70%5D%7D",
            "expires": "2028-01-25T07:09:55.000Z",
            "maxAge": 77760000,
            "domain": "b2b.daisan.vn",
            "path": "/",
            "hostOnly": true,
            "creation": "2025-08-08T07:09:54.205Z",
            "lastAccessed": "2025-08-08T07:09:54.205Z"
          }
        ]
      },
      "userData": {},
      "maxErrorScore": 3,
      "errorScoreDecrement": 0.5,
      "expiresAt": "2025-08-08T07:59:53.870Z",
      "createdAt": "2025-08-08T07:09:53.870Z",
      "usageCount": 1,
      "maxUsageCount": 50,
      "errorScore": 0
    },
    {
      "id": "session_VSIJPFGFeq",
      "cookieJar": {
        "version": "tough-cookie@5.1.2",
        "storeType": "MemoryCookieStore",
        "rejectPublicSuffixes": true,
        "enableLooseMode": false,
        "allowSpecialUseDomain": true,
        "prefixSecurity": "silent",
        "cookies": [
          {
            "key": "PHPSESSID",
            "value": "41qh49idtv1l2aot1k8cbc7lb9",
            "domain": "b2b.daisan.vn",
            "path": "/",
            "hostOnly": true,
            "creation": "2025-08-08T07:09:54.059Z",
            "lastAccessed": "2025-08-08T07:09:54.059Z"
          },
          {
            "key": "HodineCache",
            "value": "%7B%22product_view%22%3A%5B%22411818%22%5D%2C%22category_view%22%3A%5B70%5D%7D",
            "expires": "2028-01-25T07:09:55.000Z",
            "maxAge": 77760000,
            "domain": "b2b.daisan.vn",
            "path": "/",
            "hostOnly": true,
            "creation": "2025-08-08T07:09:54.059Z",
            "lastAccessed": "2025-08-08T07:09:54.059Z"
          }
        ]
      },
      "userData": {},
      "maxErrorScore": 3,
      "errorScoreDecrement": 0.5,
      "expiresAt": "2025-08-08T07:59:53.874Z",
      "createdAt": "2025-08-08T07:09:53.874Z",
      "usageCount": 1,
      "maxUsageCount": 50,
      "errorScore": 0
    },
    {
      "id": "session_j7P6Br5hGa",
      "cookieJar": {
        "version": "tough-cookie@5.1.2",
        "storeType": "MemoryCookieStore",
        "rejectPublicSuffixes": true,
        "enableLooseMode": false,
        "allowSpecialUseDomain": true,
        "prefixSecurity": "silent",
        "cookies": [
          {
            "key": "PHPSESSID",
            "value": "d12hvvklpihhu57ii2nd94vm73",
            "domain": "b2b.daisan.vn",
            "path": "/",
            "hostOnly": true,
            "creation": "2025-08-08T07:09:54.128Z",
            "lastAccessed": "2025-08-08T07:09:54.128Z"
          },
          {
            "key": "HodineCache",
            "value": "%7B%22product_view%22%3A%5B%22411774%22%5D%2C%22category_view%22%3A%5B70%5D%7D",
            "expires": "2028-01-25T07:09:55.000Z",
            "maxAge": 77760000,
            "domain": "b2b.daisan.vn",
            "path": "/",
            "hostOnly": true,
            "creation": "2025-08-08T07:09:54.128Z",
            "lastAccessed": "2025-08-08T07:09:54.128Z"
          }
        ]
      },
      "userData": {},
      "maxErrorScore": 3,
      "errorScoreDecrement": 0.5,
      "expiresAt": "2025-08-08T07:59:53.877Z",
      "createdAt": "2025-08-08T07:09:53.877Z",
      "usageCount": 1,
      "maxUsageCount": 50,
      "errorScore": 0
    },
    {
      "id": "session_VwleenUex6",
      "cookieJar": {
        "version": "tough-cookie@5.1.2",
        "storeType": "MemoryCookieStore",
        "rejectPublicSuffixes": true,
        "enableLooseMode": false,
        "allowSpecialUseDomain": true,
        "prefixSecurity": "silent",
        "cookies": [
          {
            "key": "PHPSESSID",
            "value": "f2s5vqvjkfkiv0n7fbqm302omb",
            "domain": "b2b.daisan.vn",
            "path": "/",
            "hostOnly": true,
            "creation": "2025-08-08T07:09:54.249Z",
            "lastAccessed": "2025-08-08T07:09:54.249Z"
          },
          {
            "key": "HodineCache",
            "value": "%7B%22product_view%22%3A%5B%22411817%22%5D%2C%22category_view%22%3A%5B70%5D%7D",
            "expires": "2028-01-25T07:09:55.000Z",
            "maxAge": 77760000,
            "domain": "b2b.daisan.vn",
            "path": "/",
            "hostOnly": true,
            "creation": "2025-08-08T07:09:54.249Z",
            "lastAccessed": "2025-08-08T07:09:54.249Z"
          }
        ]
      },
      "userData": {},
      "maxErrorScore": 3,
      "errorScoreDecrement": 0.5,
      "expiresAt": "2025-08-08T07:59:53.880Z",
      "createdAt": "2025-08-08T07:09:53.880Z",
      "usageCount": 1,
      "maxUsageCount": 50,
      "errorScore": 0
    },
    {
      "id": "session_ON2s3BVCAb",
      "cookieJar": {
        "version": "tough-cookie@5.1.2",
        "storeType": "MemoryCookieStore",
        "rejectPublicSuffixes": true,
        "enableLooseMode": false,
        "allowSpecialUseDomain": true,
        "prefixSecurity": "silent",
        "cookies": [
          {
            "key": "PHPSESSID",
            "value": "kqookcglf8eeam2pv4m9tk46an",
            "domain": "b2b.daisan.vn",
            "path": "/",
            "hostOnly": true,
            "creation": "2025-08-08T07:09:54.284Z",
            "lastAccessed": "2025-08-08T07:09:54.284Z"
          },
          {
            "key": "HodineCache",
            "value": "%7B%22product_view%22%3A%5B%22141899%22%5D%2C%22category_view%22%3A%5B70%5D%7D",
            "expires": "2028-01-25T07:09:55.000Z",
            "maxAge": 77760000,
            "domain": "b2b.daisan.vn",
            "path": "/",
            "hostOnly": true,
            "creation": "2025-08-08T07:09:54.284Z",
            "lastAccessed": "2025-08-08T07:09:54.284Z"
          }
        ]
      },
      "userData": {},
      "maxErrorScore": 3,
      "errorScoreDecrement": 0.5,
      "expiresAt": "2025-08-08T07:59:53.883Z",
      "createdAt": "2025-08-08T07:09:53.883Z",
      "usageCount": 1,
      "maxUsageCount": 50,
      "errorScore": 0
    },
    {
      "id": "session_DwLDWQZNEI",
      "cookieJar": {
        "version": "tough-cookie@5.1.2",
        "storeType": "MemoryCookieStore",
        "rejectPublicSuffixes": true,
        "enableLooseMode": false,
        "allowSpecialUseDomain": true,
        "prefixSecurity": "silent",
        "cookies": [
          {
            "key": "PHPSESSID",
            "value": "ik0m2nkfahgeka3a2lg2ka2tb4",
            "domain": "b2b.daisan.vn",
            "path": "/",
            "hostOnly": true,
            "creation": "2025-08-08T07:09:54.312Z",
            "lastAccessed": "2025-08-08T07:09:54.312Z"
          },
          {
            "key": "HodineCache",
            "value": "%7B%22product_view%22%3A%5B%22141905%22%5D%2C%22category_view%22%3A%5B70%5D%7D",
            "expires": "2028-01-25T07:09:55.000Z",
            "maxAge": 77760000,
            "domain": "b2b.daisan.vn",
            "path": "/",
            "hostOnly": true,
            "creation": "2025-08-08T07:09:54.312Z",
            "lastAccessed": "2025-08-08T07:09:54.312Z"
          }
        ]
      },
      "userData": {},
      "maxErrorScore": 3,
      "errorScoreDecrement": 0.5,
      "expiresAt": "2025-08-08T07:59:53.886Z",
      "createdAt": "2025-08-08T07:09:53.886Z",
      "usageCount": 1,
      "maxUsageCount": 50,
      "errorScore": 0
    },
    {
      "id": "session_rXcAuVGUF9",
      "cookieJar": {
        "version": "tough-cookie@5.1.2",
        "storeType": "MemoryCookieStore",
        "rejectPublicSuffixes": true,
        "enableLooseMode": false,
        "allowSpecialUseDomain": true,
        "prefixSecurity": "silent",
        "cookies": [
          {
            "key": "PHPSESSID",
            "value": "kr5ii0p8njmv7irc722g818se5",
            "domain": "b2b.daisan.vn",
            "path": "/",
            "hostOnly": true,
            "creation": "2025-08-08T07:09:54.367Z",
            "lastAccessed": "2025-08-08T07:09:54.367Z"
          },
          {
            "key": "HodineCache",
            "value": "%7B%22product_view%22%3A%5B%22469627%22%5D%2C%22category_view%22%3A%5B70%5D%7D",
            "expires": "2028-01-25T07:09:55.000Z",
            "maxAge": 77760000,
            "domain": "b2b.daisan.vn",
            "path": "/",
            "hostOnly": true,
            "creation": "2025-08-08T07:09:54.367Z",
            "lastAccessed": "2025-08-08T07:09:54.367Z"
          }
        ]
      },
      "userData": {},
      "maxErrorScore": 3,
      "errorScoreDecrement": 0.5,
      "expiresAt": "2025-08-08T07:59:53.889Z",
      "createdAt": "2025-08-08T07:09:53.889Z",
      "usageCount": 1,
      "maxUsageCount": 50,
      "errorScore": 0
    },
    {
      "id": "session_KYcb3QEKZc",
      "cookieJar": {
        "version": "tough-cookie@5.1.2",
        "storeType": "MemoryCookieStore",
        "rejectPublicSuffixes": true,
        "enableLooseMode": false,
        "allowSpecialUseDomain": true,
        "prefixSecurity": "silent",
        "cookies": [
          {
            "key": "PHPSESSID",
            "value": "op9djmo8erbi5ser0vhtl685pp",
            "domain": "b2b.daisan.vn",
            "path": "/",
            "hostOnly": true,
            "creation": "2025-08-08T07:09:54.100Z",
            "lastAccessed": "2025-08-08T07:09:54.100Z"
          },
          {
            "key": "HodineCache",
            "value": "%7B%22product_view%22%3A%5B%22411819%22%5D%2C%22category_view%22%3A%5B70%5D%7D",
            "expires": "2028-01-25T07:09:55.000Z",
            "maxAge": 77760000,
            "domain": "b2b.daisan.vn",
            "path": "/",
            "hostOnly": true,
            "creation": "2025-08-08T07:09:54.100Z",
            "lastAccessed": "2025-08-08T07:09:54.100Z"
          }
        ]
      },
      "userData": {},
      "maxErrorScore": 3,
      "errorScoreDecrement": 0.5,
      "expiresAt": "2025-08-08T07:59:53.893Z",
      "createdAt": "2025-08-08T07:09:53.893Z",
      "usageCount": 1,
      "maxUsageCount": 50,
      "errorScore": 0
    },
    {
      "id": "session_BdUtvHD6lF",
      "cookieJar": {
        "version": "tough-cookie@5.1.2",
        "storeType": "MemoryCookieStore",
        "rejectPublicSuffixes": true,
        "enableLooseMode": false,
        "allowSpecialUseDomain": true,
        "prefixSecurity": "silent",
        "cookies": [
          {
            "key": "PHPSESSID",
            "value": "h8fh1v744kk9f8ru6kj4n3hb1h",
            "domain": "b2b.daisan.vn",
            "path": "/",
            "hostOnly": true,
            "creation": "2025-08-08T07:09:54.339Z",
            "lastAccessed": "2025-08-08T07:09:54.339Z"
          },
          {
            "key": "HodineCache",
            "value": "%7B%22product_view%22%3A%5B%22432724%22%5D%2C%22category_view%22%3A%5B70%5D%7D",
            "expires": "2028-01-25T07:09:56.000Z",
            "maxAge": 77760000,
            "domain": "b2b.daisan.vn",
            "path": "/",
            "hostOnly": true,
            "creation": "2025-08-08T07:09:54.339Z",
            "lastAccessed": "2025-08-08T07:09:54.339Z"
          }
        ]
      },
      "userData": {},
      "maxErrorScore": 3,
      "errorScoreDecrement": 0.5,
      "expiresAt": "2025-08-08T07:59:54.035Z",
      "createdAt": "2025-08-08T07:09:54.035Z",
      "usageCount": 1,
      "maxUsageCount": 50,
      "errorScore": 0
    },
    {
      "id": "session_49XFc2M6ZE",
      "cookieJar": {
        "version": "tough-cookie@5.1.2",
        "storeType": "MemoryCookieStore",
        "rejectPublicSuffixes": true,
        "enableLooseMode": false,
        "allowSpecialUseDomain": true,
        "prefixSecurity": "silent",
        "cookies": [
          {
            "key": "PHPSESSID",
            "value": "edo9jhmdhcopn7s5u763fl211b",
            "domain": "b2b.daisan.vn",
            "path": "/",
            "hostOnly": true,
            "creation": "2025-08-08T07:09:54.423Z",
            "lastAccessed": "2025-08-08T07:09:54.423Z"
          },
          {
            "key": "HodineCache",
            "value": "%7B%22product_view%22%3A%5B%22469626%22%5D%2C%22category_view%22%3A%5B70%5D%7D",
            "expires": "2028-01-25T07:09:56.000Z",
            "maxAge": 77760000,
            "domain": "b2b.daisan.vn",
            "path": "/",
            "hostOnly": true,
            "creation": "2025-08-08T07:09:54.423Z",
            "lastAccessed": "2025-08-08T07:09:54.423Z"
          }
        ]
      },
      "userData": {},
      "maxErrorScore": 3,
      "errorScoreDecrement": 0.5,
      "expiresAt": "2025-08-08T07:59:54.226Z",
      "createdAt": "2025-08-08T07:09:54.226Z",
      "usageCount": 1,
      "maxUsageCount": 50,
      "errorScore": 0
    },
    {
      "id": "session_JnvkxyslbM",
      "cookieJar": {
        "version": "tough-cookie@5.1.2",
        "storeType": "MemoryCookieStore",
        "rejectPublicSuffixes": true,
        "enableLooseMode": false,
        "allowSpecialUseDomain": true,
        "prefixSecurity": "silent",
        "cookies": [
          {
            "key": "PHPSESSID",
            "value": "l5b0oggia3kml44e8isn0kp644",
            "domain": "b2b.daisan.vn",
            "path": "/",
            "hostOnly": true,
            "creation": "2025-08-08T07:09:54.472Z",
            "lastAccessed": "2025-08-08T07:09:54.472Z"
          },
          {
            "key": "HodineCache",
            "value": "%7B%22product_view%22%3A%5B%22411820%22%5D%2C%22category_view%22%3A%5B70%5D%7D",
            "expires": "2028-01-25T07:09:56.000Z",
            "maxAge": 77760000,
            "domain": "b2b.daisan.vn",
            "path": "/",
            "hostOnly": true,
            "creation": "2025-08-08T07:09:54.472Z",
            "lastAccessed": "2025-08-08T07:09:54.472Z"
          }
        ]
      },
      "userData": {},
      "maxErrorScore": 3,
      "errorScoreDecrement": 0.5,
      "expiresAt": "2025-08-08T07:59:54.264Z",
      "createdAt": "2025-08-08T07:09:54.264Z",
      "usageCount": 1,
      "maxUsageCount": 50,
      "errorScore": 0
    },
    {
      "id": "session_BVnCjFJPhD",
      "cookieJar": {
        "version": "tough-cookie@5.1.2",
        "storeType": "MemoryCookieStore",
        "rejectPublicSuffixes": true,
        "enableLooseMode": false,
        "allowSpecialUseDomain": true,
        "prefixSecurity": "silent",
        "cookies": [
          {
            "key": "PHPSESSID",
            "value": "s9occn784a5bnfam98ov7v8d8n",
            "domain": "b2b.daisan.vn",
            "path": "/",
            "hostOnly": true,
            "creation": "2025-08-08T07:09:54.526Z",
            "lastAccessed": "2025-08-08T07:09:54.526Z"
          },
          {
            "key": "HodineCache",
            "value": "%7B%22product_view%22%3A%5B%221577950%22%5D%2C%22category_view%22%3A%5B70%5D%7D",
            "expires": "2028-01-25T07:09:56.000Z",
            "maxAge": 77760000,
            "domain": "b2b.daisan.vn",
            "path": "/",
            "hostOnly": true,
            "creation": "2025-08-08T07:09:54.526Z",
            "lastAccessed": "2025-08-08T07:09:54.526Z"
          }
        ]
      },
      "userData": {},
      "maxErrorScore": 3,
      "errorScoreDecrement": 0.5,
      "expiresAt": "2025-08-08T07:59:54.266Z",
      "createdAt": "2025-08-08T07:09:54.266Z",
      "usageCount": 1,
      "maxUsageCount": 50,
      "errorScore": 0
    },
    {
      "id": "session_SlQ2GCpsgZ",
      "cookieJar": {
        "version": "tough-cookie@5.1.2",
        "storeType": "MemoryCookieStore",
        "rejectPublicSuffixes": true,
        "enableLooseMode": false,
        "allowSpecialUseDomain": true,
        "prefixSecurity": "silent",
        "cookies": [
          {
            "key": "PHPSESSID",
            "value": "ldr5pfljr84iccv7nvg5vbuc7h",
            "domain": "b2b.daisan.vn",
            "path": "/",
            "hostOnly": true,
            "creation": "2025-08-08T07:09:54.498Z",
            "lastAccessed": "2025-08-08T07:09:54.498Z"
          },
          {
            "key": "HodineCache",
            "value": "%7B%22product_view%22%3A%5B%22473386%22%5D%2C%22category_view%22%3A%5B70%5D%7D",
            "expires": "2028-01-25T07:09:56.000Z",
            "maxAge": 77760000,
            "domain": "b2b.daisan.vn",
            "path": "/",
            "hostOnly": true,
            "creation": "2025-08-08T07:09:54.498Z",
            "lastAccessed": "2025-08-08T07:09:54.498Z"
          }
        ]
      },
      "userData": {},
      "maxErrorScore": 3,
      "errorScoreDecrement": 0.5,
      "expiresAt": "2025-08-08T07:59:54.268Z",
      "createdAt": "2025-08-08T07:09:54.268Z",
      "usageCount": 1,
      "maxUsageCount": 50,
      "errorScore": 0
    },
    {
      "id": "session_WH51hBp8A4",
      "cookieJar": {
        "version": "tough-cookie@5.1.2",
        "storeType": "MemoryCookieStore",
        "rejectPublicSuffixes": true,
        "enableLooseMode": false,
        "allowSpecialUseDomain": true,
        "prefixSecurity": "silent",
        "cookies": [
          {
            "key": "PHPSESSID",
            "value": "4cn63aogai8gj4d9sq5osorijj",
            "domain": "b2b.daisan.vn",
            "path": "/",
            "hostOnly": true,
            "creation": "2025-08-08T07:09:54.450Z",
            "lastAccessed": "2025-08-08T07:09:54.450Z"
          },
          {
            "key": "HodineCache",
            "value": "%7B%22product_view%22%3A%5B%22376216%22%5D%2C%22category_view%22%3A%5B70%5D%7D",
            "expires": "2028-01-25T07:09:56.000Z",
            "maxAge": 77760000,
            "domain": "b2b.daisan.vn",
            "path": "/",
            "hostOnly": true,
            "creation": "2025-08-08T07:09:54.450Z",
            "lastAccessed": "2025-08-08T07:09:54.450Z"
          }
        ]
      },
      "userData": {},
      "maxErrorScore": 3,
      "errorScoreDecrement": 0.5,
      "expiresAt": "2025-08-08T07:59:54.270Z",
      "createdAt": "2025-08-08T07:09:54.270Z",
      "usageCount": 1,
      "maxUsageCount": 50,
      "errorScore": 0
    },
    {
      "id": "session_bCoLOgi3rw",
      "cookieJar": {
        "version": "tough-cookie@5.1.2",
        "storeType": "MemoryCookieStore",
        "rejectPublicSuffixes": true,
        "enableLooseMode": false,
        "allowSpecialUseDomain": true,
        "prefixSecurity": "silent",
        "cookies": [
          {
            "key": "PHPSESSID",
            "value": "uqchc3idevo55iicbj80e88hvk",
            "domain": "b2b.daisan.vn",
            "path": "/",
            "hostOnly": true,
            "creation": "2025-08-08T07:09:54.680Z",
            "lastAccessed": "2025-08-08T07:09:54.680Z"
          },
          {
            "key": "HodineCache",
            "value": "%7B%22product_view%22%3A%5B%22473392%22%5D%2C%22category_view%22%3A%5B70%5D%7D",
            "expires": "2028-01-25T07:09:56.000Z",
            "maxAge": 77760000,
            "domain": "b2b.daisan.vn",
            "path": "/",
            "hostOnly": true,
            "creation": "2025-08-08T07:09:54.680Z",
            "lastAccessed": "2025-08-08T07:09:54.680Z"
          }
        ]
      },
      "userData": {},
      "maxErrorScore": 3,
      "errorScoreDecrement": 0.5,
      "expiresAt": "2025-08-08T07:59:54.385Z",
      "createdAt": "2025-08-08T07:09:54.385Z",
      "usageCount": 1,
      "maxUsageCount": 50,
      "errorScore": 0
    },
    {
      "id": "session_GedEkgo7u0",
      "cookieJar": {
        "version": "tough-cookie@5.1.2",
        "storeType": "MemoryCookieStore",
        "rejectPublicSuffixes": true,
        "enableLooseMode": false,
        "allowSpecialUseDomain": true,
        "prefixSecurity": "silent",
        "cookies": [
          {
            "key": "PHPSESSID",
            "value": "sd0v25foiq3l379qa8p2micnb6",
            "domain": "b2b.daisan.vn",
            "path": "/",
            "hostOnly": true,
            "creation": "2025-08-08T07:09:54.627Z",
            "lastAccessed": "2025-08-08T07:09:54.627Z"
          },
          {
            "key": "HodineCache",
            "value": "%7B%22product_view%22%3A%5B%22473394%22%5D%2C%22category_view%22%3A%5B70%5D%7D",
            "expires": "2028-01-25T07:09:56.000Z",
            "maxAge": 77760000,
            "domain": "b2b.daisan.vn",
            "path": "/",
            "hostOnly": true,
            "creation": "2025-08-08T07:09:54.627Z",
            "lastAccessed": "2025-08-08T07:09:54.627Z"
          }
        ]
      },
      "userData": {},
      "maxErrorScore": 3,
      "errorScoreDecrement": 0.5,
      "expiresAt": "2025-08-08T07:59:54.392Z",
      "createdAt": "2025-08-08T07:09:54.392Z",
      "usageCount": 1,
      "maxUsageCount": 50,
      "errorScore": 0
    },
    {
      "id": "session_p3lcl1R55j",
      "cookieJar": {
        "version": "tough-cookie@5.1.2",
        "storeType": "MemoryCookieStore",
        "rejectPublicSuffixes": true,
        "enableLooseMode": false,
        "allowSpecialUseDomain": true,
        "prefixSecurity": "silent",
        "cookies": [
          {
            "key": "PHPSESSID",
            "value": "367a5ss6f8kkho90bpmg73p696",
            "domain": "b2b.daisan.vn",
            "path": "/",
            "hostOnly": true,
            "creation": "2025-08-08T07:09:54.579Z",
            "lastAccessed": "2025-08-08T07:09:54.579Z"
          },
          {
            "key": "HodineCache",
            "value": "%7B%22product_view%22%3A%5B%22658010%22%5D%2C%22category_view%22%3A%5B70%5D%7D",
            "expires": "2028-01-25T07:09:56.000Z",
            "maxAge": 77760000,
            "domain": "b2b.daisan.vn",
            "path": "/",
            "hostOnly": true,
            "creation": "2025-08-08T07:09:54.579Z",
            "lastAccessed": "2025-08-08T07:09:54.579Z"
          }
        ]
      },
      "userData": {},
      "maxErrorScore": 3,
      "errorScoreDecrement": 0.5,
      "expiresAt": "2025-08-08T07:59:54.400Z",
      "createdAt": "2025-08-08T07:09:54.400Z",
      "usageCount": 1,
      "maxUsageCount": 50,
      "errorScore": 0
    },
    {
      "id": "session_UYWrOcgsLX",
      "cookieJar": {
        "version": "tough-cookie@5.1.2",
        "storeType": "MemoryCookieStore",
        "rejectPublicSuffixes": true,
        "enableLooseMode": false,
        "allowSpecialUseDomain": true,
        "prefixSecurity": "silent",
        "cookies": [
          {
            "key": "PHPSESSID",
            "value": "6brtbuc9p6rp97b87ets5iuqpi",
            "domain": "b2b.daisan.vn",
            "path": "/",
            "hostOnly": true,
            "creation": "2025-08-08T07:09:54.601Z",
            "lastAccessed": "2025-08-08T07:09:54.601Z"
          },
          {
            "key": "HodineCache",
            "value": "%7B%22product_view%22%3A%5B%22432721%22%5D%2C%22category_view%22%3A%5B70%5D%7D",
            "expires": "2028-01-25T07:09:56.000Z",
            "maxAge": 77760000,
            "domain": "b2b.daisan.vn",
            "path": "/",
            "hostOnly": true,
            "creation": "2025-08-08T07:09:54.601Z",
            "lastAccessed": "2025-08-08T07:09:54.601Z"
          }
        ]
      },
      "userData": {},
      "maxErrorScore": 3,
      "errorScoreDecrement": 0.5,
      "expiresAt": "2025-08-08T07:59:54.403Z",
      "createdAt": "2025-08-08T07:09:54.403Z",
      "usageCount": 1,
      "maxUsageCount": 50,
      "errorScore": 0
    },
    {
      "id": "session_d2pKsyFIea",
      "cookieJar": {
        "version": "tough-cookie@5.1.2",
        "storeType": "MemoryCookieStore",
        "rejectPublicSuffixes": true,
        "enableLooseMode": false,
        "allowSpecialUseDomain": true,
        "prefixSecurity": "silent",
        "cookies": [
          {
            "key": "PHPSESSID",
            "value": "ogu5sgmk1t79s5ivqmh8njlee9",
            "domain": "b2b.daisan.vn",
            "path": "/",
            "hostOnly": true,
            "creation": "2025-08-08T07:09:54.656Z",
            "lastAccessed": "2025-08-08T07:09:54.656Z"
          },
          {
            "key": "HodineCache",
            "value": "%7B%22product_view%22%3A%5B%22141903%22%5D%2C%22category_view%22%3A%5B70%5D%7D",
            "expires": "2028-01-25T07:09:56.000Z",
            "maxAge": 77760000,
            "domain": "b2b.daisan.vn",
            "path": "/",
            "hostOnly": true,
            "creation": "2025-08-08T07:09:54.656Z",
            "lastAccessed": "2025-08-08T07:09:54.656Z"
          }
        ]
      },
      "userData": {},
      "maxErrorScore": 3,
      "errorScoreDecrement": 0.5,
      "expiresAt": "2025-08-08T07:59:54.405Z",
      "createdAt": "2025-08-08T07:09:54.405Z",
      "usageCount": 1,
      "maxUsageCount": 50,
      "errorScore": 0
    },
    {
      "id": "session_hEUKczxueX",
      "cookieJar": {
        "version": "tough-cookie@5.1.2",
        "storeType": "MemoryCookieStore",
        "rejectPublicSuffixes": true,
        "enableLooseMode": false,
        "allowSpecialUseDomain": true,
        "prefixSecurity": "silent",
        "cookies": [
          {
            "key": "PHPSESSID",
            "value": "rl0qlmvg5ifom21o8cpivvf88d",
            "domain": "b2b.daisan.vn",
            "path": "/",
            "hostOnly": true,
            "creation": "2025-08-08T07:09:54.763Z",
            "lastAccessed": "2025-08-08T07:09:54.763Z"
          },
          {
            "key": "HodineCache",
            "value": "%7B%22product_view%22%3A%5B%22141907%22%5D%2C%22category_view%22%3A%5B70%5D%7D",
            "expires": "2028-01-25T07:09:56.000Z",
            "maxAge": 77760000,
            "domain": "b2b.daisan.vn",
            "path": "/",
            "hostOnly": true,
            "creation": "2025-08-08T07:09:54.763Z",
            "lastAccessed": "2025-08-08T07:09:54.763Z"
          }
        ]
      },
      "userData": {},
      "maxErrorScore": 3,
      "errorScoreDecrement": 0.5,
      "expiresAt": "2025-08-08T07:59:54.549Z",
      "createdAt": "2025-08-08T07:09:54.549Z",
      "usageCount": 1,
      "maxUsageCount": 50,
      "errorScore": 0
    },
    {
      "id": "session_FU4V0ls1yA",
      "cookieJar": {
        "version": "tough-cookie@5.1.2",
        "storeType": "MemoryCookieStore",
        "rejectPublicSuffixes": true,
        "enableLooseMode": false,
        "allowSpecialUseDomain": true,
        "prefixSecurity": "silent",
        "cookies": [
          {
            "key": "PHPSESSID",
            "value": "5inpv7eskbsr9u8h7b33v7vko1",
            "domain": "b2b.daisan.vn",
            "path": "/",
            "hostOnly": true,
            "creation": "2025-08-08T07:09:54.787Z",
            "lastAccessed": "2025-08-08T07:09:54.787Z"
          },
          {
            "key": "HodineCache",
            "value": "%7B%22product_view%22%3A%5B%22469695%22%5D%2C%22category_view%22%3A%5B70%5D%7D",
            "expires": "2028-01-25T07:09:56.000Z",
            "maxAge": 77760000,
            "domain": "b2b.daisan.vn",
            "path": "/",
            "hostOnly": true,
            "creation": "2025-08-08T07:09:54.787Z",
            "lastAccessed": "2025-08-08T07:09:54.787Z"
          }
        ]
      },
      "userData": {},
      "maxErrorScore": 3,
      "errorScoreDecrement": 0.5,
      "expiresAt": "2025-08-08T07:59:54.552Z",
      "createdAt": "2025-08-08T07:09:54.552Z",
      "usageCount": 1,
      "maxUsageCount": 50,
      "errorScore": 0
    },
    {
      "id": "session_NTCBfhwbUX",
      "cookieJar": {
        "version": "tough-cookie@5.1.2",
        "storeType": "MemoryCookieStore",
        "rejectPublicSuffixes": true,
        "enableLooseMode": false,
        "allowSpecialUseDomain": true,
        "prefixSecurity": "silent",
        "cookies": [
          {
            "key": "PHPSESSID",
            "value": "bhv80t0o7ksqm2ccp1ta65q0qq",
            "domain": "b2b.daisan.vn",
            "path": "/",
            "hostOnly": true,
            "creation": "2025-08-08T07:09:54.732Z",
            "lastAccessed": "2025-08-08T07:09:54.732Z"
          },
          {
            "key": "HodineCache",
            "value": "%7B%22product_view%22%3A%5B%22141902%22%5D%2C%22category_view%22%3A%5B70%5D%7D",
            "expires": "2028-01-25T07:09:56.000Z",
            "maxAge": 77760000,
            "domain": "b2b.daisan.vn",
            "path": "/",
            "hostOnly": true,
            "creation": "2025-08-08T07:09:54.732Z",
            "lastAccessed": "2025-08-08T07:09:54.732Z"
          }
        ]
      },
      "userData": {},
      "maxErrorScore": 3,
      "errorScoreDecrement": 0.5,
      "expiresAt": "2025-08-08T07:59:54.554Z",
      "createdAt": "2025-08-08T07:09:54.554Z",
      "usageCount": 1,
      "maxUsageCount": 50,
      "errorScore": 0
    },
    {
      "id": "session_F3sMmc8h0t",
      "cookieJar": {
        "version": "tough-cookie@5.1.2",
        "storeType": "MemoryCookieStore",
        "rejectPublicSuffixes": true,
        "enableLooseMode": false,
        "allowSpecialUseDomain": true,
        "prefixSecurity": "silent",
        "cookies": [
          {
            "key": "PHPSESSID",
            "value": "qd4ictavk5unb5e7vf8gltuth7",
            "domain": "b2b.daisan.vn",
            "path": "/",
            "hostOnly": true,
            "creation": "2025-08-08T07:09:55.020Z",
            "lastAccessed": "2025-08-08T07:09:55.020Z"
          },
          {
            "key": "HodineCache",
            "value": "%7B%22product_view%22%3A%5B%22657937%22%5D%2C%22category_view%22%3A%5B70%5D%7D",
            "expires": "2028-01-25T07:09:56.000Z",
            "maxAge": 77760000,
            "domain": "b2b.daisan.vn",
            "path": "/",
            "hostOnly": true,
            "creation": "2025-08-08T07:09:55.021Z",
            "lastAccessed": "2025-08-08T07:09:55.021Z"
          }
        ]
      },
      "userData": {},
      "maxErrorScore": 3,
      "errorScoreDecrement": 0.5,
      "expiresAt": "2025-08-08T07:59:54.829Z",
      "createdAt": "2025-08-08T07:09:54.829Z",
      "usageCount": 1,
      "maxUsageCount": 50,
      "errorScore": 0
    },
    {
      "id": "session_D1nxxaEKsZ",
      "cookieJar": {
        "version": "tough-cookie@5.1.2",
        "storeType": "MemoryCookieStore",
        "rejectPublicSuffixes": true,
        "enableLooseMode": false,
        "allowSpecialUseDomain": true,
        "prefixSecurity": "silent",
        "cookies": [
          {
            "key": "PHPSESSID",
            "value": "4udsdj7n61dnn6jcdc6pv1kjif",
            "domain": "b2b.daisan.vn",
            "path": "/",
            "hostOnly": true,
            "creation": "2025-08-08T07:09:55.051Z",
            "lastAccessed": "2025-08-08T07:09:55.051Z"
          },
          {
            "key": "HodineCache",
            "value": "%7B%22product_view%22%3A%5B%22753224%22%5D%2C%22category_view%22%3A%5B70%5D%7D",
            "expires": "2028-01-25T07:09:56.000Z",
            "maxAge": 77760000,
            "domain": "b2b.daisan.vn",
            "path": "/",
            "hostOnly": true,
            "creation": "2025-08-08T07:09:55.051Z",
            "lastAccessed": "2025-08-08T07:09:55.051Z"
          }
        ]
      },
      "userData": {},
      "maxErrorScore": 3,
      "errorScoreDecrement": 0.5,
      "expiresAt": "2025-08-08T07:59:54.833Z",
      "createdAt": "2025-08-08T07:09:54.833Z",
      "usageCount": 1,
      "maxUsageCount": 50,
      "errorScore": 0
    },
    {
      "id": "session_2bt4YNlZWi",
      "cookieJar": {
        "version": "tough-cookie@5.1.2",
        "storeType": "MemoryCookieStore",
        "rejectPublicSuffixes": true,
        "enableLooseMode": false,
        "allowSpecialUseDomain": true,
        "prefixSecurity": "silent",
        "cookies": [
          {
            "key": "PHPSESSID",
            "value": "drl1du808dqdof2a9jgk4vvjia",
            "domain": "b2b.daisan.vn",
            "path": "/",
            "hostOnly": true,
            "creation": "2025-08-08T07:09:54.959Z",
            "lastAccessed": "2025-08-08T07:09:54.959Z"
          },
          {
            "key": "HodineCache",
            "value": "%7B%22product_view%22%3A%5B%22479080%22%5D%2C%22category_view%22%3A%5B70%5D%7D",
            "expires": "2028-01-25T07:09:56.000Z",
            "maxAge": 77760000,
            "domain": "b2b.daisan.vn",
            "path": "/",
            "hostOnly": true,
            "creation": "2025-08-08T07:09:54.959Z",
            "lastAccessed": "2025-08-08T07:09:54.959Z"
          }
        ]
      },
      "userData": {},
      "maxErrorScore": 3,
      "errorScoreDecrement": 0.5,
      "expiresAt": "2025-08-08T07:59:54.836Z",
      "createdAt": "2025-08-08T07:09:54.836Z",
      "usageCount": 1,
      "maxUsageCount": 50,
      "errorScore": 0
    },
    {
      "id": "session_yjfEy60Gbu",
      "cookieJar": {
        "version": "tough-cookie@5.1.2",
        "storeType": "MemoryCookieStore",
        "rejectPublicSuffixes": true,
        "enableLooseMode": false,
        "allowSpecialUseDomain": true,
        "prefixSecurity": "silent",
        "cookies": [
          {
            "key": "PHPSESSID",
            "value": "dqbrjueobdgtc813jk3g5mjgbj",
            "domain": "b2b.daisan.vn",
            "path": "/",
            "hostOnly": true,
            "creation": "2025-08-08T07:09:54.933Z",
            "lastAccessed": "2025-08-08T07:09:54.933Z"
          },
          {
            "key": "HodineCache",
            "value": "%7B%22product_view%22%3A%5B%221613155%22%5D%2C%22category_view%22%3A%5B70%5D%7D",
            "expires": "2028-01-25T07:09:56.000Z",
            "maxAge": 77760000,
            "domain": "b2b.daisan.vn",
            "path": "/",
            "hostOnly": true,
            "creation": "2025-08-08T07:09:54.933Z",
            "lastAccessed": "2025-08-08T07:09:54.933Z"
          }
        ]
      },
      "userData": {},
      "maxErrorScore": 3,
      "errorScoreDecrement": 0.5,
      "expiresAt": "2025-08-08T07:59:54.838Z",
      "createdAt": "2025-08-08T07:09:54.838Z",
      "usageCount": 1,
      "maxUsageCount": 50,
      "errorScore": 0
    },
    {
      "id": "session_aoKnpr9HhP",
      "cookieJar": {
        "version": "tough-cookie@5.1.2",
        "storeType": "MemoryCookieStore",
        "rejectPublicSuffixes": true,
        "enableLooseMode": false,
        "allowSpecialUseDomain": true,
        "prefixSecurity": "silent",
        "cookies": [
          {
            "key": "PHPSESSID",
            "value": "utnnk2rrv09gr89tnatdnq7ilf",
            "domain": "b2b.daisan.vn",
            "path": "/",
            "hostOnly": true,
            "creation": "2025-08-08T07:09:55.090Z",
            "lastAccessed": "2025-08-08T07:09:55.090Z"
          },
          {
            "key": "HodineCache",
            "value": "%7B%22product_view%22%3A%5B%221613161%22%5D%2C%22category_view%22%3A%5B70%5D%7D",
            "expires": "2028-01-25T07:09:56.000Z",
            "maxAge": 77760000,
            "domain": "b2b.daisan.vn",
            "path": "/",
            "hostOnly": true,
            "creation": "2025-08-08T07:09:55.090Z",
            "lastAccessed": "2025-08-08T07:09:55.090Z"
          }
        ]
      },
      "userData": {},
      "maxErrorScore": 3,
      "errorScoreDecrement": 0.5,
      "expiresAt": "2025-08-08T07:59:54.840Z",
      "createdAt": "2025-08-08T07:09:54.840Z",
      "usageCount": 1,
      "maxUsageCount": 50,
      "errorScore": 0
    },
    {
      "id": "session_qCrLID3nWj",
      "cookieJar": {
        "version": "tough-cookie@5.1.2",
        "storeType": "MemoryCookieStore",
        "rejectPublicSuffixes": true,
        "enableLooseMode": false,
        "allowSpecialUseDomain": true,
        "prefixSecurity": "silent",
        "cookies": [
          {
            "key": "PHPSESSID",
            "value": "6v5as30l0or7n3l3co1hrmgv9p",
            "domain": "b2b.daisan.vn",
            "path": "/",
            "hostOnly": true,
            "creation": "2025-08-08T07:09:54.993Z",
            "lastAccessed": "2025-08-08T07:09:54.993Z"
          },
          {
            "key": "HodineCache",
            "value": "%7B%22product_view%22%3A%5B%22432716%22%5D%2C%22category_view%22%3A%5B70%5D%7D",
            "expires": "2028-01-25T07:09:56.000Z",
            "maxAge": 77760000,
            "domain": "b2b.daisan.vn",
            "path": "/",
            "hostOnly": true,
            "creation": "2025-08-08T07:09:54.993Z",
            "lastAccessed": "2025-08-08T07:09:54.993Z"
          }
        ]
      },
      "userData": {},
      "maxErrorScore": 3,
      "errorScoreDecrement": 0.5,
      "expiresAt": "2025-08-08T07:59:54.845Z",
      "createdAt": "2025-08-08T07:09:54.845Z",
      "usageCount": 1,
      "maxUsageCount": 50,
      "errorScore": 0
    },
    {
      "id": "session_XYzkgMYjHW",
      "cookieJar": {
        "version": "tough-cookie@5.1.2",
        "storeType": "MemoryCookieStore",
        "rejectPublicSuffixes": true,
        "enableLooseMode": false,
        "allowSpecialUseDomain": true,
        "prefixSecurity": "silent",
        "cookies": [
          {
            "key": "PHPSESSID",
            "value": "v3otp2an90elfgi46964hnau60",
            "domain": "b2b.daisan.vn",
            "path": "/",
            "hostOnly": true,
            "creation": "2025-08-08T07:09:55.120Z",
            "lastAccessed": "2025-08-08T07:09:55.120Z"
          },
          {
            "key": "HodineCache",
            "value": "%7B%22product_view%22%3A%5B%221577959%22%5D%2C%22category_view%22%3A%5B70%5D%7D",
            "expires": "2028-01-25T07:09:56.000Z",
            "maxAge": 77760000,
            "domain": "b2b.daisan.vn",
            "path": "/",
            "hostOnly": true,
            "creation": "2025-08-08T07:09:55.120Z",
            "lastAccessed": "2025-08-08T07:09:55.120Z"
          }
        ]
      },
      "userData": {},
      "maxErrorScore": 3,
      "errorScoreDecrement": 0.5,
      "expiresAt": "2025-08-08T07:59:54.857Z",
      "createdAt": "2025-08-08T07:09:54.857Z",
      "usageCount": 1,
      "maxUsageCount": 50,
      "errorScore": 0
    }
  ]
}